ensemble/__init__.py
ensemble/explainer.py
transparency-0.0.1.dist-info/METADATA
transparency-0.0.1.dist-info/RECORD
transparency-0.0.1.dist-info/WHEEL
transparency-0.0.1.dist-info/top_level.txt
